winzy_whitelist/__init__.py
winzy_whitelist-0.0.1.dist-info/LICENSE
winzy_whitelist-0.0.1.dist-info/METADATA
winzy_whitelist-0.0.1.dist-info/WHEEL
winzy_whitelist-0.0.1.dist-info/entry_points.txt
winzy_whitelist-0.0.1.dist-info/top_level.txt
winzy_whitelist-0.0.1.dist-info/RECORD
