Metadata-Version: 2.1
Name: winzy-whitelist
Version: 0.0.1
Summary: Whitelist python created exe's to make them bat scripts.
Author: Sukhbinder Singh
License: Apache-2.0
Project-URL: Homepage, https://github.com/sukhbinder/winzy-whitelist
Project-URL: Changelog, https://github.com/sukhbinder/winzy-whitelist/releases
Project-URL: Issues, https://github.com/sukhbinder/winzy-whitelist/issues
Project-URL: CI, https://github.com/sukhbinder/winzy-whitelist/actions
Classifier: License :: OSI Approved :: Apache Software License
License-File: LICENSE
Requires-Dist: winzy
Provides-Extra: test
Requires-Dist: pytest; extra == "test"
